{
  "retail_records": [
    {
      "address": "1 146 W 29th St",
      "city_state": "",
      "page_number": 1,
      "spaces": [
        {
          "floor": "GRND",
          "suite": "Retail",
          "use_type": "Retail",
          "size_sf": "1500",
          "rent_per_sf": "Withheld",
          "page_number": 1
        },
        {
          "floor": "GRND",
          "suite": "2",
          "use_type": "Retail",
          "size_sf": "1919",
          "rent_per_sf": "$7.82",
          "page_number": 1
        },
        {
          "floor": "",
          "suite": "Retail",
          "use_type": "Retail",
          "size_sf": "1500",
          "rent_per_sf": "$9.00",
          "page_number": 1
        }
      ]
    },
    {
      "address": "4 261 3rd Ave",
      "city_state": "",
      "page_number": 6,
      "spaces": [
        {
          "floor": "GRND",
          "suite": "Corner",
          "use_type": "Retail",
          "size_sf": "700",
          "rent_per_sf": "Withheld",
          "page_number": 6
        },
        {
          "floor": "GRND",
          "suite": "-",
          "use_type": "Retail",
          "size_sf": "1505",
          "rent_per_sf": "Withheld",
          "page_number": 6
        },
        {
          "floor": "GRND",
          "suite": "117",
          "use_type": "Retail",
          "size_sf": "1600",
          "rent_per_sf": "Withheld",
          "page_number": 6
        },
        {
          "floor": "GRND",
          "suite": "-",
          "use_type": "Retail",
          "size_sf": "1690",
          "rent_per_sf": "Withheld",
          "page_number": 6
        }
      ]
    },
    {
      "address": "5 139 E 23rd St",
      "city_state": "",
      "page_number": 7,
      "spaces": [
        {
          "floor": "GRND",
          "suite": "-",
          "use_type": "Retail",
          "size_sf": "1505",
          "rent_per_sf": "Withheld",
          "page_number": 7
        },
        {
          "floor": "GRND",
          "suite": "117",
          "use_type": "Retail",
          "size_sf": "1600",
          "rent_per_sf": "Withheld",
          "page_number": 7
        },
        {
          "floor": "GRND",
          "suite": "-",
          "use_type": "Retail",
          "size_sf": "1690",
          "rent_per_sf": "Withheld",
          "page_number": 7
        },
        {
          "floor": "GRND",
          "suite": "-",
          "use_type": "Retail",
          "size_sf": "1600",
          "rent_per_sf": "Withheld",
          "page_number": 7
        }
      ]
    },
    {
      "address": "7 11 Penn Pl",
      "city_state": "",
      "page_number": 10,
      "spaces": [
        {
          "floor": "GRND",
          "suite": "-",
          "use_type": "Retail",
          "size_sf": "1690",
          "rent_per_sf": "Withheld",
          "page_number": 10
        },
        {
          "floor": "GRND",
          "suite": "-",
          "use_type": "Retail",
          "size_sf": "1600",
          "rent_per_sf": "Withheld",
          "page_number": 10
        },
        {
          "floor": "GRND",
          "suite": "-",
          "use_type": "Office/Retail",
          "size_sf": "1665",
          "rent_per_sf": "$8.75",
          "page_number": 10
        }
      ]
    },
    {
      "address": "8 311 Second Ave",
      "city_state": "",
      "page_number": 11,
      "spaces": [
        {
          "floor": "GRND",
          "suite": "-",
          "use_type": "Retail",
          "size_sf": "1600",
          "rent_per_sf": "Withheld",
          "page_number": 11
        },
        {
          "floor": "GRND",
          "suite": "-",
          "use_type": "Office/Retail",
          "size_sf": "1665",
          "rent_per_sf": "$8.75",
          "page_number": 11
        }
      ]
    },
    {
      "address": "9 146 W 4th St",
      "city_state": "",
      "page_number": 13,
      "spaces": [
        {
          "floor": "GRND",
          "suite": "-",
          "use_type": "Office/Retail",
          "size_sf": "1665",
          "rent_per_sf": "$8.75",
          "page_number": 13
        },
        {
          "floor": "GRND",
          "suite": "Upper",
          "use_type": "Retail",
          "size_sf": "1520",
          "rent_per_sf": "$5.00",
          "page_number": 13
        }
      ]
    },
    {
      "address": "11 28 W 12th St",
      "city_state": "",
      "page_number": 17,
      "spaces": [
        {
          "floor": "GRND",
          "suite": "Upper",
          "use_type": "Retail",
          "size_sf": "1520",
          "rent_per_sf": "$5.00",
          "page_number": 17
        },
        {
          "floor": "GRND",
          "suite": "1W",
          "use_type": "Retail",
          "size_sf": "1806",
          "rent_per_sf": "$8.31",
          "page_number": 17
        },
        {
          "floor": "GRND",
          "suite": "-",
          "use_type": "Retail",
          "size_sf": "2000",
          "rent_per_sf": "$13.33",
          "page_number": 17
        }
      ]
    },
    {
      "address": "12 123 W 20th St",
      "city_state": "",
      "page_number": 19,
      "spaces": [
        {
          "floor": "GRND",
          "suite": "1W",
          "use_type": "Retail",
          "size_sf": "1806",
          "rent_per_sf": "$8.31",
          "page_number": 19
        },
        {
          "floor": "GRND",
          "suite": "-",
          "use_type": "Retail",
          "size_sf": "2000",
          "rent_per_sf": "$13.33",
          "page_number": 19
        },
        {
          "floor": "GRND",
          "suite": "-",
          "use_type": "Retail",
          "size_sf": "1000",
          "rent_per_sf": "$6.66",
          "page_number": 19
        }
      ]
    },
    {
      "address": "13 36 E 23rd St",
      "city_state": "",
      "page_number": 21,
      "spaces": [
        {
          "floor": "GRND",
          "suite": "-",
          "use_type": "Retail",
          "size_sf": "2000",
          "rent_per_sf": "$13.33",
          "page_number": 21
        },
        {
          "floor": "GRND",
          "suite": "-",
          "use_type": "Retail",
          "size_sf": "1000",
          "rent_per_sf": "$6.66",
          "page_number": 21
        },
        {
          "floor": "GRND",
          "suite": "-",
          "use_type": "Retail",
          "size_sf": "1400",
          "rent_per_sf": "$5.76",
          "page_number": 21
        }
      ]
    },
    {
      "address": "15 150 W 26th St",
      "city_state": "",
      "page_number": 24,
      "spaces": [
        {
          "floor": "GRND",
          "suite": "-",
          "use_type": "Retail",
          "size_sf": "1400",
          "rent_per_sf": "$5.76",
          "page_number": 24
        },
        {
          "floor": "GRND",
          "suite": "-",
          "use_type": "Retail",
          "size_sf": "1800",
          "rent_per_sf": "$8.08",
          "page_number": 24
        },
        {
          "floor": "",
          "suite": "-",
          "use_type": "Retail",
          "size_sf": "1050",
          "rent_per_sf": "$12.38",
          "page_number": 24
        }
      ]
    },
    {
      "address": "16 149 W 27th St",
      "city_state": "",
      "page_number": 26,
      "spaces": [
        {
          "floor": "GRND",
          "suite": "-",
          "use_type": "Retail",
          "size_sf": "1800",
          "rent_per_sf": "$8.08",
          "page_number": 26
        },
        {
          "floor": "",
          "suite": "-",
          "use_type": "Retail",
          "size_sf": "1050",
          "rent_per_sf": "$12.38",
          "page_number": 26
        },
        {
          "floor": "GRND",
          "suite": "-",
          "use_type": "Office/Retail",
          "size_sf": "1806",
          "rent_per_sf": "Withheld",
          "page_number": 26
        },
        {
          "floor": "",
          "suite": "Space",
          "use_type": "Retail",
          "size_sf": "1335",
          "rent_per_sf": "Withheld",
          "page_number": 26
        }
      ]
    },
    {
      "address": "17 113 E 29th St",
      "city_state": "",
      "page_number": 27,
      "spaces": [
        {
          "floor": "",
          "suite": "-",
          "use_type": "Retail",
          "size_sf": "1050",
          "rent_per_sf": "$12.38",
          "page_number": 27
        },
        {
          "floor": "GRND",
          "suite": "-",
          "use_type": "Office/Retail",
          "size_sf": "1806",
          "rent_per_sf": "Withheld",
          "page_number": 27
        },
        {
          "floor": "",
          "suite": "Space",
          "use_type": "Retail",
          "size_sf": "1335",
          "rent_per_sf": "Withheld",
          "page_number": 27
        },
        {
          "floor": "GRND",
          "suite": "-",
          "use_type": "Retail",
          "size_sf": "1700",
          "rent_per_sf": "$3.25",
          "page_number": 27
        }
      ]
    },
    {
      "address": "19 160 Bleecker St",
      "city_state": "",
      "page_number": 30,
      "spaces": [
        {
          "floor": "",
          "suite": "Space",
          "use_type": "Retail",
          "size_sf": "1335",
          "rent_per_sf": "Withheld",
          "page_number": 30
        },
        {
          "floor": "GRND",
          "suite": "-",
          "use_type": "Retail",
          "size_sf": "1700",
          "rent_per_sf": "$3.25",
          "page_number": 30
        },
        {
          "floor": "",
          "suite": "-",
          "use_type": "Retail",
          "size_sf": "1500",
          "rent_per_sf": "$10.50",
          "page_number": 30
        }
      ]
    },
    {
      "address": "22 244 Eighth Ave",
      "city_state": "",
      "page_number": 35,
      "spaces": [
        {
          "floor": "GRND",
          "suite": "-",
          "use_type": "Retail",
          "size_sf": "1500",
          "rent_per_sf": "$10.67",
          "page_number": 35
        },
        {
          "floor": "GRND",
          "suite": "-",
          "use_type": "Retail",
          "size_sf": "950",
          "rent_per_sf": "Withheld",
          "page_number": 35
        },
        {
          "floor": "GRND",
          "suite": "-",
          "use_type": "Retail",
          "size_sf": "800",
          "rent_per_sf": "$12.92",
          "page_number": 35
        }
      ]
    },
    {
      "address": "23 230 Fifth Ave",
      "city_state": "",
      "page_number": 37,
      "spaces": [
        {
          "floor": "GRND",
          "suite": "-",
          "use_type": "Retail",
          "size_sf": "950",
          "rent_per_sf": "Withheld",
          "page_number": 37
        },
        {
          "floor": "GRND",
          "suite": "-",
          "use_type": "Retail",
          "size_sf": "800",
          "rent_per_sf": "$12.92",
          "page_number": 37
        },
        {
          "floor": "GRND",
          "suite": "-",
          "use_type": "Retail",
          "size_sf": "1500",
          "rent_per_sf": "$87.27",
          "page_number": 37
        }
      ]
    },
    {
      "address": "24 148 Madison Ave",
      "city_state": "",
      "page_number": 39,
      "spaces": [
        {
          "floor": "GRND",
          "suite": "-",
          "use_type": "Retail",
          "size_sf": "950",
          "rent_per_sf": "Withheld",
          "page_number": 39
        },
        {
          "floor": "GRND",
          "suite": "-",
          "use_type": "Retail",
          "size_sf": "800",
          "rent_per_sf": "$12.92",
          "page_number": 39
        },
        {
          "floor": "GRND",
          "suite": "-",
          "use_type": "Retail",
          "size_sf": "1500",
          "rent_per_sf": "$87.27",
          "page_number": 39
        },
        {
          "floor": "GRND",
          "suite": "-",
          "use_type": "Retail",
          "size_sf": "1500",
          "rent_per_sf": "$10.00",
          "page_number": 39
        }
      ]
    },
    {
      "address": "25 437 Park Ave",
      "city_state": "",
      "page_number": 40,
      "spaces": [
        {
          "floor": "GRND",
          "suite": "-",
          "use_type": "Retail",
          "size_sf": "800",
          "rent_per_sf": "$12.92",
          "page_number": 40
        },
        {
          "floor": "GRND",
          "suite": "-",
          "use_type": "Retail",
          "size_sf": "1500",
          "rent_per_sf": "$87.27",
          "page_number": 40
        },
        {
          "floor": "GRND",
          "suite": "-",
          "use_type": "Retail",
          "size_sf": "1500",
          "rent_per_sf": "$10.00",
          "page_number": 40
        }
      ]
    },
    {
      "address": "26 133 Second Ave",
      "city_state": "",
      "page_number": 42,
      "spaces": [
        {
          "floor": "GRND",
          "suite": "-",
          "use_type": "Retail",
          "size_sf": "1500",
          "rent_per_sf": "$87.27",
          "page_number": 42
        },
        {
          "floor": "GRND",
          "suite": "-",
          "use_type": "Retail",
          "size_sf": "1500",
          "rent_per_sf": "$10.00",
          "page_number": 42
        }
      ]
    },
    {
      "address": "27 5 St  Marks Pl",
      "city_state": "",
      "page_number": 44,
      "spaces": [
        {
          "floor": "GRND",
          "suite": "-",
          "use_type": "Retail",
          "size_sf": "1500",
          "rent_per_sf": "$10.00",
          "page_number": 44
        },
        {
          "floor": "GRND",
          "suite": "A",
          "use_type": "Retail",
          "size_sf": "1466",
          "rent_per_sf": "Withheld",
          "page_number": 44
        }
      ]
    },
    {
      "address": "29 85 4th Ave",
      "city_state": "",
      "page_number": 47,
      "spaces": [
        {
          "floor": "GRND",
          "suite": "A",
          "use_type": "Retail",
          "size_sf": "1466",
          "rent_per_sf": "Withheld",
          "page_number": 47
        },
        {
          "floor": "GRND",
          "suite": "C",
          "use_type": "Retail",
          "size_sf": "1040",
          "rent_per_sf": "Withheld",
          "page_number": 47
        },
        {
          "floor": "GRND",
          "suite": "D",
          "use_type": "Retail",
          "size_sf": "694",
          "rent_per_sf": "Withheld",
          "page_number": 47
        },
        {
          "floor": "GRND",
          "suite": "B",
          "use_type": "Retail",
          "size_sf": "578",
          "rent_per_sf": "Withheld",
          "page_number": 47
        },
        {
          "floor": "GRND",
          "suite": "-",
          "use_type": "Retail",
          "size_sf": "1785",
          "rent_per_sf": "Withheld",
          "page_number": 47
        }
      ]
    },
    {
      "address": "30 120 7th Ave",
      "city_state": "",
      "page_number": 49,
      "spaces": [
        {
          "floor": "GRND",
          "suite": "C",
          "use_type": "Retail",
          "size_sf": "1040",
          "rent_per_sf": "Withheld",
          "page_number": 49
        },
        {
          "floor": "GRND",
          "suite": "D",
          "use_type": "Retail",
          "size_sf": "694",
          "rent_per_sf": "Withheld",
          "page_number": 49
        },
        {
          "floor": "GRND",
          "suite": "B",
          "use_type": "Retail",
          "size_sf": "578",
          "rent_per_sf": "Withheld",
          "page_number": 49
        },
        {
          "floor": "GRND",
          "suite": "-",
          "use_type": "Retail",
          "size_sf": "1785",
          "rent_per_sf": "Withheld",
          "page_number": 49
        },
        {
          "floor": "",
          "suite": "21",
          "use_type": "Retail",
          "size_sf": "2000",
          "rent_per_sf": "Withheld",
          "page_number": 49
        }
      ]
    },
    {
      "address": "33 60 E 8th St",
      "city_state": "",
      "page_number": 54,
      "spaces": [
        {
          "floor": "",
          "suite": "747",
          "use_type": "Retail",
          "size_sf": "1250",
          "rent_per_sf": "Withheld",
          "page_number": 54
        },
        {
          "floor": "GRND",
          "suite": "-",
          "use_type": "Retail",
          "size_sf": "2000",
          "rent_per_sf": "Withheld",
          "page_number": 54
        },
        {
          "floor": "",
          "suite": "Commu-",
          "use_type": "Retail",
          "size_sf": "1027",
          "rent_per_sf": "Withheld",
          "page_number": 54
        }
      ]
    },
    {
      "address": "34 58 E 11th St",
      "city_state": "",
      "page_number": 56,
      "spaces": [
        {
          "floor": "GRND",
          "suite": "-",
          "use_type": "Retail",
          "size_sf": "2000",
          "rent_per_sf": "Withheld",
          "page_number": 56
        },
        {
          "floor": "",
          "suite": "Commu-",
          "use_type": "Retail",
          "size_sf": "1027",
          "rent_per_sf": "Withheld",
          "page_number": 56
        },
        {
          "floor": "",
          "suite": "-",
          "use_type": "Retail",
          "size_sf": "1452",
          "rent_per_sf": "Withheld",
          "page_number": 56
        }
      ]
    },
    {
      "address": "35 21 E 12th St",
      "city_state": "",
      "page_number": 57,
      "spaces": [
        {
          "floor": "",
          "suite": "Commu-",
          "use_type": "Retail",
          "size_sf": "1027",
          "rent_per_sf": "Withheld",
          "page_number": 57
        },
        {
          "floor": "",
          "suite": "-",
          "use_type": "Retail",
          "size_sf": "1452",
          "rent_per_sf": "Withheld",
          "page_number": 57
        },
        {
          "floor": "GRND",
          "suite": "A",
          "use_type": "Retail",
          "size_sf": "1265",
          "rent_per_sf": "Withheld",
          "page_number": 57
        },
        {
          "floor": "GRND",
          "suite": "B",
          "use_type": "Retail",
          "size_sf": "807",
          "rent_per_sf": "Withheld",
          "page_number": 57
        }
      ]
    },
    {
      "address": "38 212 W 14th St",
      "city_state": "",
      "page_number": 63,
      "spaces": [
        {
          "floor": "GRND",
          "suite": "-",
          "use_type": "Retail",
          "size_sf": "1600",
          "rent_per_sf": "Withheld",
          "page_number": 63
        },
        {
          "floor": "GRND",
          "suite": "-",
          "use_type": "Retail",
          "size_sf": "2000",
          "rent_per_sf": "Withheld",
          "page_number": 63
        },
        {
          "floor": "",
          "suite": "555",
          "use_type": "Retail",
          "size_sf": "1290",
          "rent_per_sf": "Withheld",
          "page_number": 63
        }
      ]
    },
    {
      "address": "39 232 W 14th St",
      "city_state": "",
      "page_number": 65,
      "spaces": [
        {
          "floor": "GRND",
          "suite": "-",
          "use_type": "Retail",
          "size_sf": "2000",
          "rent_per_sf": "Withheld",
          "page_number": 65
        },
        {
          "floor": "",
          "suite": "555",
          "use_type": "Retail",
          "size_sf": "1290",
          "rent_per_sf": "Withheld",
          "page_number": 65
        },
        {
          "floor": "GRND",
          "suite": "-",
          "use_type": "Retail",
          "size_sf": "1700",
          "rent_per_sf": "Withheld",
          "page_number": 65
        }
      ]
    },
    {
      "address": "40 101 W 15th St",
      "city_state": "",
      "page_number": 67,
      "spaces": [
        {
          "floor": "",
          "suite": "555",
          "use_type": "Retail",
          "size_sf": "1290",
          "rent_per_sf": "Withheld",
          "page_number": 67
        },
        {
          "floor": "GRND",
          "suite": "-",
          "use_type": "Retail",
          "size_sf": "1700",
          "rent_per_sf": "Withheld",
          "page_number": 67
        },
        {
          "floor": "GRND",
          "suite": "-",
          "use_type": "Retail",
          "size_sf": "1868",
          "rent_per_sf": "Withheld",
          "page_number": 67
        }
      ]
    },
    {
      "address": "41 17 E 17th St",
      "city_state": "",
      "page_number": 69,
      "spaces": [
        {
          "floor": "GRND",
          "suite": "-",
          "use_type": "Retail",
          "size_sf": "1700",
          "rent_per_sf": "Withheld",
          "page_number": 69
        },
        {
          "floor": "GRND",
          "suite": "-",
          "use_type": "Retail",
          "size_sf": "1868",
          "rent_per_sf": "Withheld",
          "page_number": 69
        },
        {
          "floor": "GRND",
          "suite": "-",
          "use_type": "Retail",
          "size_sf": "1098",
          "rent_per_sf": "Withheld",
          "page_number": 69
        }
      ]
    },
    {
      "address": "42 21 W 17th St",
      "city_state": "",
      "page_number": 70,
      "spaces": [
        {
          "floor": "GRND",
          "suite": "-",
          "use_type": "Retail",
          "size_sf": "1868",
          "rent_per_sf": "Withheld",
          "page_number": 70
        },
        {
          "floor": "GRND",
          "suite": "-",
          "use_type": "Retail",
          "size_sf": "1098",
          "rent_per_sf": "Withheld",
          "page_number": 70
        },
        {
          "floor": "GRND",
          "suite": "-",
          "use_type": "Retail",
          "size_sf": "2000",
          "rent_per_sf": "Withheld",
          "page_number": 70
        }
      ]
    },
    {
      "address": "43 16 W 18th St",
      "city_state": "",
      "page_number": 72,
      "spaces": [
        {
          "floor": "GRND",
          "suite": "-",
          "use_type": "Retail",
          "size_sf": "1098",
          "rent_per_sf": "Withheld",
          "page_number": 72
        },
        {
          "floor": "GRND",
          "suite": "-",
          "use_type": "Retail",
          "size_sf": "2000",
          "rent_per_sf": "Withheld",
          "page_number": 72
        }
      ]
    },
    {
      "address": "44 200 E 20th St",
      "city_state": "",
      "page_number": 74,
      "spaces": [
        {
          "floor": "GRND",
          "suite": "-",
          "use_type": "Retail",
          "size_sf": "1098",
          "rent_per_sf": "Withheld",
          "page_number": 74
        },
        {
          "floor": "GRND",
          "suite": "-",
          "use_type": "Retail",
          "size_sf": "2000",
          "rent_per_sf": "Withheld",
          "page_number": 74
        },
        {
          "floor": "GRND",
          "suite": "-",
          "use_type": "Retail",
          "size_sf": "2000",
          "rent_per_sf": "Withheld",
          "page_number": 74
        }
      ]
    },
    {
      "address": "45 44 W 22nd St",
      "city_state": "",
      "page_number": 75,
      "spaces": [
        {
          "floor": "GRND",
          "suite": "-",
          "use_type": "Retail",
          "size_sf": "2000",
          "rent_per_sf": "Withheld",
          "page_number": 75
        },
        {
          "floor": "GRND",
          "suite": "-",
          "use_type": "Retail",
          "size_sf": "2000",
          "rent_per_sf": "Withheld",
          "page_number": 75
        },
        {
          "floor": "",
          "suite": "-",
          "use_type": "Retail",
          "size_sf": "2000",
          "rent_per_sf": "Withheld",
          "page_number": 75
        }
      ]
    },
    {
      "address": "46 18 E 23rd St",
      "city_state": "",
      "page_number": 77,
      "spaces": [
        {
          "floor": "GRND",
          "suite": "-",
          "use_type": "Retail",
          "size_sf": "2000",
          "rent_per_sf": "Withheld",
          "page_number": 77
        },
        {
          "floor": "",
          "suite": "-",
          "use_type": "Retail",
          "size_sf": "2000",
          "rent_per_sf": "Withheld",
          "page_number": 77
        },
        {
          "floor": "GRND",
          "suite": "-",
          "use_type": "Retail",
          "size_sf": "1700",
          "rent_per_sf": "Withheld",
          "page_number": 77
        }
      ]
    },
    {
      "address": "48 170 W 23rd St",
      "city_state": "",
      "page_number": 81,
      "spaces": [
        {
          "floor": "GRND",
          "suite": "-",
          "use_type": "Retail",
          "size_sf": "1700",
          "rent_per_sf": "Withheld",
          "page_number": 81
        },
        {
          "floor": "GRND",
          "suite": "-",
          "use_type": "Retail",
          "size_sf": "1100",
          "rent_per_sf": "Withheld",
          "page_number": 81
        },
        {
          "floor": "GRND",
          "suite": "-",
          "use_type": "Retail",
          "size_sf": "1600",
          "rent_per_sf": "Withheld",
          "page_number": 81
        }
      ]
    },
    {
      "address": "50 77 W 24th St",
      "city_state": "",
      "page_number": 85,
      "spaces": [
        {
          "floor": "GRND",
          "suite": "-",
          "use_type": "Retail",
          "size_sf": "1600",
          "rent_per_sf": "Withheld",
          "page_number": 85
        },
        {
          "floor": "GRND",
          "suite": "-",
          "use_type": "Retail",
          "size_sf": "1467",
          "rent_per_sf": "Withheld",
          "page_number": 85
        }
      ]
    },
    {
      "address": "51 200 W 26th St",
      "city_state": "",
      "page_number": 87,
      "spaces": [
        {
          "floor": "GRND",
          "suite": "-",
          "use_type": "Retail",
          "size_sf": "1467",
          "rent_per_sf": "Withheld",
          "page_number": 87
        }
      ]
    },
    {
      "address": "52 118 E 28th St",
      "city_state": "",
      "page_number": 90,
      "spaces": [
        {
          "floor": "GRND",
          "suite": "A",
          "use_type": "Retail",
          "size_sf": "1190",
          "rent_per_sf": "Withheld",
          "page_number": 90
        },
        {
          "floor": "GRND",
          "suite": "-",
          "use_type": "Retail",
          "size_sf": "1275",
          "rent_per_sf": "Withheld",
          "page_number": 90
        }
      ]
    },
    {
      "address": "53 243 W 28th St",
      "city_state": "",
      "page_number": 91,
      "spaces": [
        {
          "floor": "GRND",
          "suite": "A",
          "use_type": "Retail",
          "size_sf": "1190",
          "rent_per_sf": "Withheld",
          "page_number": 91
        },
        {
          "floor": "GRND",
          "suite": "-",
          "use_type": "Retail",
          "size_sf": "1275",
          "rent_per_sf": "Withheld",
          "page_number": 91
        }
      ]
    },
    {
      "address": "54 14 W 29th St",
      "city_state": "",
      "page_number": 93,
      "spaces": [
        {
          "floor": "GRND",
          "suite": "-",
          "use_type": "Retail",
          "size_sf": "1275",
          "rent_per_sf": "Withheld",
          "page_number": 93
        },
        {
          "floor": "GRND",
          "suite": "-",
          "use_type": "Retail",
          "size_sf": "2000",
          "rent_per_sf": "Withheld",
          "page_number": 93
        },
        {
          "floor": "GRND",
          "suite": "-",
          "use_type": "Retail",
          "size_sf": "1300",
          "rent_per_sf": "Withheld",
          "page_number": 93
        },
        {
          "floor": "GRND",
          "suite": "-",
          "use_type": "Retail",
          "size_sf": "1200",
          "rent_per_sf": "Withheld",
          "page_number": 93
        }
      ]
    },
    {
      "address": "55 102 W 29th St",
      "city_state": "",
      "page_number": 95,
      "spaces": [
        {
          "floor": "GRND",
          "suite": "-",
          "use_type": "Retail",
          "size_sf": "2000",
          "rent_per_sf": "Withheld",
          "page_number": 95
        },
        {
          "floor": "GRND",
          "suite": "-",
          "use_type": "Retail",
          "size_sf": "1300",
          "rent_per_sf": "Withheld",
          "page_number": 95
        },
        {
          "floor": "GRND",
          "suite": "-",
          "use_type": "Retail",
          "size_sf": "1200",
          "rent_per_sf": "Withheld",
          "page_number": 95
        }
      ]
    },
    {
      "address": "56 140 W 30th St",
      "city_state": "",
      "page_number": 97,
      "spaces": [
        {
          "floor": "GRND",
          "suite": "-",
          "use_type": "Retail",
          "size_sf": "1300",
          "rent_per_sf": "Withheld",
          "page_number": 97
        },
        {
          "floor": "GRND",
          "suite": "-",
          "use_type": "Retail",
          "size_sf": "1200",
          "rent_per_sf": "Withheld",
          "page_number": 97
        },
        {
          "floor": "GRND",
          "suite": "-",
          "use_type": "Retail",
          "size_sf": "1300",
          "rent_per_sf": "Withheld",
          "page_number": 97
        }
      ]
    },
    {
      "address": "60 45 Bleecker St",
      "city_state": "",
      "page_number": 103,
      "spaces": [
        {
          "floor": "GRND",
          "suite": "-",
          "use_type": "Retail",
          "size_sf": "1415",
          "rent_per_sf": "Withheld",
          "page_number": 103
        },
        {
          "floor": "GRND",
          "suite": "-",
          "use_type": "Retail",
          "size_sf": "1900",
          "rent_per_sf": "Withheld",
          "page_number": 103
        },
        {
          "floor": "GRND",
          "suite": "774",
          "use_type": "Office/Retail",
          "size_sf": "725",
          "rent_per_sf": "Withheld",
          "page_number": 103
        }
      ]
    },
    {
      "address": "68 294 Eighth Ave",
      "city_state": "",
      "page_number": 116,
      "spaces": [
        {
          "floor": "GRND",
          "suite": "-",
          "use_type": "Retail",
          "size_sf": "2000",
          "rent_per_sf": "Withheld",
          "page_number": 116
        },
        {
          "floor": "GRND",
          "suite": "-",
          "use_type": "Retail",
          "size_sf": "1200",
          "rent_per_sf": "Withheld",
          "page_number": 116
        },
        {
          "floor": "GRND",
          "suite": "-",
          "use_type": "Office/Retail",
          "size_sf": "750",
          "rent_per_sf": "Withheld",
          "page_number": 116
        }
      ]
    },
    {
      "address": "69 79 Fifth Ave",
      "city_state": "",
      "page_number": 118,
      "spaces": [
        {
          "floor": "GRND",
          "suite": "-",
          "use_type": "Retail",
          "size_sf": "1200",
          "rent_per_sf": "Withheld",
          "page_number": 118
        },
        {
          "floor": "GRND",
          "suite": "-",
          "use_type": "Office/Retail",
          "size_sf": "750",
          "rent_per_sf": "Withheld",
          "page_number": 118
        },
        {
          "floor": "GRND",
          "suite": "-",
          "use_type": "Retail",
          "size_sf": "1500",
          "rent_per_sf": "Withheld",
          "page_number": 118
        }
      ]
    },
    {
      "address": "70 234 Fifth Ave",
      "city_state": "",
      "page_number": 119,
      "spaces": [
        {
          "floor": "GRND",
          "suite": "-",
          "use_type": "Retail",
          "size_sf": "1200",
          "rent_per_sf": "Withheld",
          "page_number": 119
        },
        {
          "floor": "GRND",
          "suite": "-",
          "use_type": "Office/Retail",
          "size_sf": "750",
          "rent_per_sf": "Withheld",
          "page_number": 119
        },
        {
          "floor": "GRND",
          "suite": "-",
          "use_type": "Retail",
          "size_sf": "1500",
          "rent_per_sf": "Withheld",
          "page_number": 119
        }
      ]
    },
    {
      "address": "71 256 Fifth Ave",
      "city_state": "",
      "page_number": 120,
      "spaces": [
        {
          "floor": "GRND",
          "suite": "-",
          "use_type": "Office/Retail",
          "size_sf": "750",
          "rent_per_sf": "Withheld",
          "page_number": 120
        },
        {
          "floor": "GRND",
          "suite": "-",
          "use_type": "Retail",
          "size_sf": "1500",
          "rent_per_sf": "Withheld",
          "page_number": 120
        },
        {
          "floor": "GRND",
          "suite": "-",
          "use_type": "Retail",
          "size_sf": "620",
          "rent_per_sf": "Withheld",
          "page_number": 120
        }
      ]
    },
    {
      "address": "72 3 Great Jones St",
      "city_state": "",
      "page_number": 122,
      "spaces": [
        {
          "floor": "GRND",
          "suite": "-",
          "use_type": "Retail",
          "size_sf": "1500",
          "rent_per_sf": "Withheld",
          "page_number": 122
        },
        {
          "floor": "GRND",
          "suite": "-",
          "use_type": "Retail",
          "size_sf": "620",
          "rent_per_sf": "Withheld",
          "page_number": 122
        },
        {
          "floor": "GRND",
          "suite": "109",
          "use_type": "Retail",
          "size_sf": "1866",
          "rent_per_sf": "Withheld",
          "page_number": 122
        },
        {
          "floor": "GRND",
          "suite": "104",
          "use_type": "Retail",
          "size_sf": "1182",
          "rent_per_sf": "Withheld",
          "page_number": 122
        }
      ]
    },
    {
      "address": "73 25 Great Jones St",
      "city_state": "",
      "page_number": 124,
      "spaces": [
        {
          "floor": "GRND",
          "suite": "-",
          "use_type": "Retail",
          "size_sf": "620",
          "rent_per_sf": "Withheld",
          "page_number": 124
        },
        {
          "floor": "GRND",
          "suite": "109",
          "use_type": "Retail",
          "size_sf": "1866",
          "rent_per_sf": "Withheld",
          "page_number": 124
        },
        {
          "floor": "GRND",
          "suite": "104",
          "use_type": "Retail",
          "size_sf": "1182",
          "rent_per_sf": "Withheld",
          "page_number": 124
        },
        {
          "floor": "GRND",
          "suite": "-",
          "use_type": "Retail",
          "size_sf": "1250",
          "rent_per_sf": "Withheld",
          "page_number": 124
        }
      ]
    },
    {
      "address": "74 1 Irving Pl",
      "city_state": "",
      "page_number": 126,
      "spaces": [
        {
          "floor": "GRND",
          "suite": "109",
          "use_type": "Retail",
          "size_sf": "1866",
          "rent_per_sf": "Withheld",
          "page_number": 126
        },
        {
          "floor": "GRND",
          "suite": "104",
          "use_type": "Retail",
          "size_sf": "1182",
          "rent_per_sf": "Withheld",
          "page_number": 126
        },
        {
          "floor": "GRND",
          "suite": "-",
          "use_type": "Retail",
          "size_sf": "1250",
          "rent_per_sf": "Withheld",
          "page_number": 126
        },
        {
          "floor": "GRND",
          "suite": "Ground",
          "use_type": "Retail",
          "size_sf": "1019",
          "rent_per_sf": "Withheld",
          "page_number": 126
        }
      ]
    },
    {
      "address": "75 372 Lafayette St",
      "city_state": "",
      "page_number": 128,
      "spaces": [
        {
          "floor": "GRND",
          "suite": "-",
          "use_type": "Retail",
          "size_sf": "1250",
          "rent_per_sf": "Withheld",
          "page_number": 128
        },
        {
          "floor": "GRND",
          "suite": "Ground",
          "use_type": "Retail",
          "size_sf": "1019",
          "rent_per_sf": "Withheld",
          "page_number": 128
        },
        {
          "floor": "GRND",
          "suite": "-",
          "use_type": "Retail",
          "size_sf": "1000",
          "rent_per_sf": "Withheld",
          "page_number": 128
        }
      ]
    },
    {
      "address": "76 445 Lafayette St",
      "city_state": "",
      "page_number": 130,
      "spaces": [
        {
          "floor": "GRND",
          "suite": "Ground",
          "use_type": "Retail",
          "size_sf": "1019",
          "rent_per_sf": "Withheld",
          "page_number": 130
        },
        {
          "floor": "GRND",
          "suite": "-",
          "use_type": "Retail",
          "size_sf": "1000",
          "rent_per_sf": "Withheld",
          "page_number": 130
        },
        {
          "floor": "GRND",
          "suite": "A",
          "use_type": "Retail",
          "size_sf": "1300",
          "rent_per_sf": "Withheld",
          "page_number": 130
        },
        {
          "floor": "GRND",
          "suite": "B",
          "use_type": "Retail",
          "size_sf": "1100",
          "rent_per_sf": "Withheld",
          "page_number": 130
        }
      ]
    },
    {
      "address": "78 121 Madison Ave",
      "city_state": "",
      "page_number": 134,
      "spaces": [
        {
          "floor": "GRND",
          "suite": "A",
          "use_type": "Retail",
          "size_sf": "1300",
          "rent_per_sf": "Withheld",
          "page_number": 134
        },
        {
          "floor": "GRND",
          "suite": "B",
          "use_type": "Retail",
          "size_sf": "1100",
          "rent_per_sf": "Withheld",
          "page_number": 134
        },
        {
          "floor": "",
          "suite": "687",
          "use_type": "Retail",
          "size_sf": "1050",
          "rent_per_sf": "Withheld",
          "page_number": 134
        },
        {
          "floor": "",
          "suite": "683",
          "use_type": "Retail",
          "size_sf": "1000",
          "rent_per_sf": "Withheld",
          "page_number": 134
        },
        {
          "floor": "GRND",
          "suite": "-",
          "use_type": "Retail",
          "size_sf": "1100",
          "rent_per_sf": "Withheld",
          "page_number": 134
        }
      ]
    },
    {
      "address": "79 250 Mercer St",
      "city_state": "",
      "page_number": 136,
      "spaces": [
        {
          "floor": "",
          "suite": "687",
          "use_type": "Retail",
          "size_sf": "1050",
          "rent_per_sf": "Withheld",
          "page_number": 136
        },
        {
          "floor": "",
          "suite": "683",
          "use_type": "Retail",
          "size_sf": "1000",
          "rent_per_sf": "Withheld",
          "page_number": 136
        },
        {
          "floor": "GRND",
          "suite": "-",
          "use_type": "Retail",
          "size_sf": "1100",
          "rent_per_sf": "Withheld",
          "page_number": 136
        },
        {
          "floor": "GRND",
          "suite": "-",
          "use_type": "Retail",
          "size_sf": "1027",
          "rent_per_sf": "Withheld",
          "page_number": 136
        },
        {
          "floor": "GRND",
          "suite": "-",
          "use_type": "Retail",
          "size_sf": "1600",
          "rent_per_sf": "Withheld",
          "page_number": 136
        }
      ]
    },
    {
      "address": "80 337 Park Ave",
      "city_state": "",
      "page_number": 138,
      "spaces": [
        {
          "floor": "GRND",
          "suite": "-",
          "use_type": "Retail",
          "size_sf": "1100",
          "rent_per_sf": "Withheld",
          "page_number": 138
        },
        {
          "floor": "GRND",
          "suite": "-",
          "use_type": "Retail",
          "size_sf": "1027",
          "rent_per_sf": "Withheld",
          "page_number": 138
        },
        {
          "floor": "GRND",
          "suite": "-",
          "use_type": "Retail",
          "size_sf": "1600",
          "rent_per_sf": "Withheld",
          "page_number": 138
        },
        {
          "floor": "GRND",
          "suite": "A",
          "use_type": "Retail",
          "size_sf": "1987",
          "rent_per_sf": "Withheld",
          "page_number": 138
        }
      ]
    },
    {
      "address": "81 470 Park Ave",
      "city_state": "",
      "page_number": 139,
      "spaces": [
        {
          "floor": "GRND",
          "suite": "-",
          "use_type": "Retail",
          "size_sf": "1027",
          "rent_per_sf": "Withheld",
          "page_number": 139
        },
        {
          "floor": "GRND",
          "suite": "-",
          "use_type": "Retail",
          "size_sf": "1600",
          "rent_per_sf": "Withheld",
          "page_number": 139
        },
        {
          "floor": "GRND",
          "suite": "A",
          "use_type": "Retail",
          "size_sf": "1987",
          "rent_per_sf": "Withheld",
          "page_number": 139
        }
      ]
    },
    {
      "address": "83 275 Seventh Ave",
      "city_state": "",
      "page_number": 142,
      "spaces": [
        {
          "floor": "GRND",
          "suite": "A",
          "use_type": "Retail",
          "size_sf": "1987",
          "rent_per_sf": "Withheld",
          "page_number": 142
        },
        {
          "floor": "GRND",
          "suite": "-",
          "use_type": "Retail",
          "size_sf": "2000",
          "rent_per_sf": "Withheld",
          "page_number": 142
        },
        {
          "floor": "GRND",
          "suite": "-",
          "use_type": "Retail",
          "size_sf": "1700",
          "rent_per_sf": "Withheld",
          "page_number": 142
        },
        {
          "floor": "GRND",
          "suite": "A",
          "use_type": "Retail",
          "size_sf": "1500",
          "rent_per_sf": "Withheld",
          "page_number": 142
        }
      ]
    },
    {
      "address": "84 287 Seventh Ave",
      "city_state": "",
      "page_number": 143,
      "spaces": [
        {
          "floor": "GRND",
          "suite": "-",
          "use_type": "Retail",
          "size_sf": "2000",
          "rent_per_sf": "Withheld",
          "page_number": 143
        },
        {
          "floor": "GRND",
          "suite": "-",
          "use_type": "Retail",
          "size_sf": "1700",
          "rent_per_sf": "Withheld",
          "page_number": 143
        },
        {
          "floor": "GRND",
          "suite": "A",
          "use_type": "Retail",
          "size_sf": "1500",
          "rent_per_sf": "Withheld",
          "page_number": 143
        }
      ]
    },
    {
      "address": "85 299 Seventh Ave",
      "city_state": "",
      "page_number": 145,
      "spaces": [
        {
          "floor": "GRND",
          "suite": "-",
          "use_type": "Retail",
          "size_sf": "1700",
          "rent_per_sf": "Withheld",
          "page_number": 145
        },
        {
          "floor": "GRND",
          "suite": "A",
          "use_type": "Retail",
          "size_sf": "1500",
          "rent_per_sf": "Withheld",
          "page_number": 145
        },
        {
          "floor": "GRND",
          "suite": "-",
          "use_type": "Retail",
          "size_sf": "1600",
          "rent_per_sf": "Withheld",
          "page_number": 145
        }
      ]
    },
    {
      "address": "86 345 Seventh Ave",
      "city_state": "",
      "page_number": 147,
      "spaces": [
        {
          "floor": "GRND",
          "suite": "A",
          "use_type": "Retail",
          "size_sf": "1500",
          "rent_per_sf": "Withheld",
          "page_number": 147
        },
        {
          "floor": "GRND",
          "suite": "-",
          "use_type": "Retail",
          "size_sf": "1600",
          "rent_per_sf": "Withheld",
          "page_number": 147
        },
        {
          "floor": "GRND",
          "suite": "-",
          "use_type": "Retail",
          "size_sf": "812",
          "rent_per_sf": "Withheld",
          "page_number": 147
        }
      ]
    },
    {
      "address": "88 388 Third Ave",
      "city_state": "",
      "page_number": 149,
      "spaces": [
        {
          "floor": "GRND",
          "suite": "-",
          "use_type": "Retail",
          "size_sf": "1600",
          "rent_per_sf": "Withheld",
          "page_number": 149
        },
        {
          "floor": "GRND",
          "suite": "-",
          "use_type": "Retail",
          "size_sf": "812",
          "rent_per_sf": "Withheld",
          "page_number": 149
        },
        {
          "floor": "GRND",
          "suite": "-",
          "use_type": "Retail",
          "size_sf": "1390",
          "rent_per_sf": "Withheld",
          "page_number": 149
        }
      ]
    },
    {
      "address": "89 441 Third Ave",
      "city_state": "",
      "page_number": 151,
      "spaces": [
        {
          "floor": "GRND",
          "suite": "-",
          "use_type": "Retail",
          "size_sf": "812",
          "rent_per_sf": "Withheld",
          "page_number": 151
        },
        {
          "floor": "GRND",
          "suite": "-",
          "use_type": "Retail",
          "size_sf": "1390",
          "rent_per_sf": "Withheld",
          "page_number": 151
        },
        {
          "floor": "GRND",
          "suite": "-",
          "use_type": "Retail",
          "size_sf": "1000",
          "rent_per_sf": "Withheld",
          "page_number": 151
        }
      ]
    },
    {
      "address": "91 11 Waverly Pl",
      "city_state": "",
      "page_number": 155,
      "spaces": [
        {
          "floor": "GRND",
          "suite": "-",
          "use_type": "Retail",
          "size_sf": "1000",
          "rent_per_sf": "Withheld",
          "page_number": 155
        }
      ]
    }
  ],
  "office_records": [
    {
      "address": "1 27 W 20th St",
      "city_state": "",
      "page_number": 1,
      "spaces": [
        {
          "floor": "12",
          "suite": "-",
          "use_type": "Office",
          "size_sf": "500",
          "rent_per_sf": "$3.00",
          "page_number": 1
        },
        {
          "floor": "10",
          "suite": "-",
          "use_type": "Office/Medical",
          "size_sf": "3005",
          "rent_per_sf": "$3.33",
          "page_number": 1
        }
      ]
    },
    {
      "address": "2 134 W 29th St",
      "city_state": "",
      "page_number": 2,
      "spaces": [
        {
          "floor": "12",
          "suite": "-",
          "use_type": "Office",
          "size_sf": "500",
          "rent_per_sf": "$3.00",
          "page_number": 2
        },
        {
          "floor": "10",
          "suite": "-",
          "use_type": "Office/Medical",
          "size_sf": "3005",
          "rent_per_sf": "$3.33",
          "page_number": 2
        }
      ]
    },
    {
      "address": "3 115 E 23rd St",
      "city_state": "",
      "page_number": 3,
      "spaces": [
        {
          "floor": "10",
          "suite": "-",
          "use_type": "Office/Medical",
          "size_sf": "3005",
          "rent_per_sf": "$3.33",
          "page_number": 3
        }
      ]
    },
    {
      "address": "4 150 W 30th St",
      "city_state": "",
      "page_number": 4,
      "spaces": []
    },
    {
      "address": "5 242 W 30th St",
      "city_state": "",
      "page_number": 6,
      "spaces": [
        {
          "floor": "2",
          "suite": "-",
          "use_type": "Office",
          "size_sf": "4911",
          "rent_per_sf": "$3.00",
          "page_number": 6
        }
      ]
    },
    {
      "address": "6 119 W 23rd St",
      "city_state": "",
      "page_number": 8,
      "spaces": [
        {
          "floor": "2",
          "suite": "-",
          "use_type": "Office",
          "size_sf": "4911",
          "rent_per_sf": "$3.00",
          "page_number": 8
        },
        {
          "floor": "2",
          "suite": "-",
          "use_type": "Office",
          "size_sf": "5000",
          "rent_per_sf": "",
          "page_number": 8
        },
        {
          "floor": "9",
          "suite": "-",
          "use_type": "Office",
          "size_sf": "5000",
          "rent_per_sf": "$3.04",
          "page_number": 8
        }
      ]
    },
    {
      "address": "7 134 W 25th St",
      "city_state": "",
      "page_number": 9,
      "spaces": [
        {
          "floor": "2",
          "suite": "-",
          "use_type": "Office",
          "size_sf": "4911",
          "rent_per_sf": "$3.00",
          "page_number": 9
        },
        {
          "floor": "2",
          "suite": "-",
          "use_type": "Office",
          "size_sf": "5000",
          "rent_per_sf": "",
          "page_number": 9
        },
        {
          "floor": "9",
          "suite": "-",
          "use_type": "Office",
          "size_sf": "5000",
          "rent_per_sf": "$3.04",
          "page_number": 9
        },
        {
          "floor": "5",
          "suite": "-",
          "use_type": "Office",
          "size_sf": "2500",
          "rent_per_sf": "$4.79",
          "page_number": 9
        },
        {
          "floor": "6",
          "suite": "-",
          "use_type": "Office",
          "size_sf": "2500",
          "rent_per_sf": "$4.79",
          "page_number": 9
        }
      ]
    },
    {
      "address": "8 134 W 26th St",
      "city_state": "",
      "page_number": 11,
      "spaces": [
        {
          "floor": "2",
          "suite": "-",
          "use_type": "Office",
          "size_sf": "5000",
          "rent_per_sf": "",
          "page_number": 11
        },
        {
          "floor": "9",
          "suite": "-",
          "use_type": "Office",
          "size_sf": "5000",
          "rent_per_sf": "$3.04",
          "page_number": 11
        },
        {
          "floor": "5",
          "suite": "-",
          "use_type": "Office",
          "size_sf": "2500",
          "rent_per_sf": "$4.79",
          "page_number": 11
        },
        {
          "floor": "6",
          "suite": "-",
          "use_type": "Office",
          "size_sf": "2500",
          "rent_per_sf": "$4.79",
          "page_number": 11
        },
        {
          "floor": "19",
          "suite": "-",
          "use_type": "Office",
          "size_sf": "1000",
          "rent_per_sf": "",
          "page_number": 11
        }
      ]
    },
    {
      "address": "9 141 W 28th St",
      "city_state": "",
      "page_number": 12,
      "spaces": [
        {
          "floor": "2",
          "suite": "-",
          "use_type": "Office",
          "size_sf": "5000",
          "rent_per_sf": "",
          "page_number": 12
        },
        {
          "floor": "9",
          "suite": "-",
          "use_type": "Office",
          "size_sf": "5000",
          "rent_per_sf": "$3.04",
          "page_number": 12
        },
        {
          "floor": "5",
          "suite": "-",
          "use_type": "Office",
          "size_sf": "2500",
          "rent_per_sf": "$4.79",
          "page_number": 12
        },
        {
          "floor": "6",
          "suite": "-",
          "use_type": "Office",
          "size_sf": "2500",
          "rent_per_sf": "$4.79",
          "page_number": 12
        },
        {
          "floor": "19",
          "suite": "-",
          "use_type": "Office",
          "size_sf": "1000",
          "rent_per_sf": "",
          "page_number": 12
        },
        {
          "floor": "2",
          "suite": "-",
          "use_type": "Office",
          "size_sf": "3300",
          "rent_per_sf": "",
          "page_number": 12
        }
      ]
    },
    {
      "address": "11 307 Seventh Ave",
      "city_state": "",
      "page_number": 14,
      "spaces": [
        {
          "floor": "19",
          "suite": "-",
          "use_type": "Office",
          "size_sf": "1000",
          "rent_per_sf": "",
          "page_number": 14
        },
        {
          "floor": "2",
          "suite": "-",
          "use_type": "Office",
          "size_sf": "3300",
          "rent_per_sf": "",
          "page_number": 14
        },
        {
          "floor": "3",
          "suite": "-",
          "use_type": "Office",
          "size_sf": "4500",
          "rent_per_sf": "",
          "page_number": 14
        }
      ]
    },
    {
      "address": "12 220 E 23rd St",
      "city_state": "",
      "page_number": 15,
      "spaces": [
        {
          "floor": "2",
          "suite": "-",
          "use_type": "Office",
          "size_sf": "3300",
          "rent_per_sf": "",
          "page_number": 15
        },
        {
          "floor": "3",
          "suite": "-",
          "use_type": "Office",
          "size_sf": "4500",
          "rent_per_sf": "",
          "page_number": 15
        },
        {
          "floor": "3",
          "suite": "-",
          "use_type": "Office",
          "size_sf": "4000",
          "rent_per_sf": "$3.75",
          "page_number": 15
        }
      ]
    },
    {
      "address": "14 281 Park Ave",
      "city_state": "",
      "page_number": 18,
      "spaces": [
        {
          "floor": "3",
          "suite": "-",
          "use_type": "Office",
          "size_sf": "4000",
          "rent_per_sf": "$3.75",
          "page_number": 18
        },
        {
          "floor": "2",
          "suite": "-",
          "use_type": "Office/Retail",
          "size_sf": "2325",
          "rent_per_sf": "$4.58",
          "page_number": 18
        },
        {
          "floor": "3",
          "suite": "-",
          "use_type": "Office/Retail",
          "size_sf": "2325",
          "rent_per_sf": "",
          "page_number": 18
        },
        {
          "floor": "3",
          "suite": "-",
          "use_type": "Office/Retail",
          "size_sf": "2500",
          "rent_per_sf": "$2.92",
          "page_number": 18
        }
      ]
    },
    {
      "address": "15 134 5th Ave",
      "city_state": "",
      "page_number": 19,
      "spaces": [
        {
          "floor": "3",
          "suite": "-",
          "use_type": "Office",
          "size_sf": "4000",
          "rent_per_sf": "$3.75",
          "page_number": 19
        },
        {
          "floor": "2",
          "suite": "-",
          "use_type": "Office/Retail",
          "size_sf": "2325",
          "rent_per_sf": "$4.58",
          "page_number": 19
        },
        {
          "floor": "3",
          "suite": "-",
          "use_type": "Office/Retail",
          "size_sf": "2325",
          "rent_per_sf": "",
          "page_number": 19
        },
        {
          "floor": "3",
          "suite": "-",
          "use_type": "Office/Retail",
          "size_sf": "2500",
          "rent_per_sf": "$2.92",
          "page_number": 19
        },
        {
          "floor": "10",
          "suite": "-",
          "use_type": "Office",
          "size_sf": "4500",
          "rent_per_sf": "$3.83",
          "page_number": 19
        }
      ]
    },
    {
      "address": "16 21 E 17th St",
      "city_state": "",
      "page_number": 20,
      "spaces": [
        {
          "floor": "2",
          "suite": "-",
          "use_type": "Office/Retail",
          "size_sf": "2325",
          "rent_per_sf": "$4.58",
          "page_number": 20
        },
        {
          "floor": "3",
          "suite": "-",
          "use_type": "Office/Retail",
          "size_sf": "2325",
          "rent_per_sf": "",
          "page_number": 20
        },
        {
          "floor": "3",
          "suite": "-",
          "use_type": "Office/Retail",
          "size_sf": "2500",
          "rent_per_sf": "$2.92",
          "page_number": 20
        },
        {
          "floor": "10",
          "suite": "-",
          "use_type": "Office",
          "size_sf": "4500",
          "rent_per_sf": "$3.83",
          "page_number": 20
        },
        {
          "floor": "3",
          "suite": "-",
          "use_type": "Office",
          "size_sf": "5000",
          "rent_per_sf": "$4.42",
          "page_number": 20
        }
      ]
    },
    {
      "address": "18 133 W 19th St",
      "city_state": "",
      "page_number": 23,
      "spaces": [
        {
          "floor": "10",
          "suite": "-",
          "use_type": "Office",
          "size_sf": "4500",
          "rent_per_sf": "$3.83",
          "page_number": 23
        },
        {
          "floor": "3",
          "suite": "-",
          "use_type": "Office",
          "size_sf": "5000",
          "rent_per_sf": "$4.42",
          "page_number": 23
        },
        {
          "floor": "7",
          "suite": "-",
          "use_type": "Office",
          "size_sf": "4300",
          "rent_per_sf": "$4.33",
          "page_number": 23
        }
      ]
    },
    {
      "address": "19 45 E 20th St",
      "city_state": "",
      "page_number": 24,
      "spaces": [
        {
          "floor": "3",
          "suite": "-",
          "use_type": "Office",
          "size_sf": "5000",
          "rent_per_sf": "$4.42",
          "page_number": 24
        },
        {
          "floor": "7",
          "suite": "-",
          "use_type": "Office",
          "size_sf": "4300",
          "rent_per_sf": "$4.33",
          "page_number": 24
        },
        {
          "floor": "5",
          "suite": "-",
          "use_type": "Office",
          "size_sf": "4000",
          "rent_per_sf": "",
          "page_number": 24
        }
      ]
    },
    {
      "address": "21 117 E 24th St",
      "city_state": "",
      "page_number": 26,
      "spaces": [
        {
          "floor": "7",
          "suite": "-",
          "use_type": "Office",
          "size_sf": "4300",
          "rent_per_sf": "$4.33",
          "page_number": 26
        },
        {
          "floor": "5",
          "suite": "-",
          "use_type": "Office",
          "size_sf": "4000",
          "rent_per_sf": "",
          "page_number": 26
        },
        {
          "floor": "4",
          "suite": "-",
          "use_type": "Office",
          "size_sf": "200",
          "rent_per_sf": "",
          "page_number": 26
        },
        {
          "floor": "7",
          "suite": "-",
          "use_type": "Office",
          "size_sf": "100",
          "rent_per_sf": "",
          "page_number": 26
        },
        {
          "floor": "8",
          "suite": "-",
          "use_type": "Office",
          "size_sf": "4000",
          "rent_per_sf": "$4.92",
          "page_number": 26
        }
      ]
    },
    {
      "address": "23 148 W 24th St",
      "city_state": "",
      "page_number": 29,
      "spaces": [
        {
          "floor": "4",
          "suite": "-",
          "use_type": "Office",
          "size_sf": "200",
          "rent_per_sf": "",
          "page_number": 29
        },
        {
          "floor": "7",
          "suite": "-",
          "use_type": "Office",
          "size_sf": "100",
          "rent_per_sf": "",
          "page_number": 29
        },
        {
          "floor": "8",
          "suite": "-",
          "use_type": "Office",
          "size_sf": "4000",
          "rent_per_sf": "$4.92",
          "page_number": 29
        },
        {
          "floor": "",
          "suite": "-",
          "use_type": "Office",
          "size_sf": "4500",
          "rent_per_sf": "$3.00",
          "page_number": 29
        }
      ]
    },
    {
      "address": "24 159 W 25th St",
      "city_state": "",
      "page_number": 30,
      "spaces": [
        {
          "floor": "4",
          "suite": "-",
          "use_type": "Office",
          "size_sf": "200",
          "rent_per_sf": "",
          "page_number": 30
        },
        {
          "floor": "7",
          "suite": "-",
          "use_type": "Office",
          "size_sf": "100",
          "rent_per_sf": "",
          "page_number": 30
        },
        {
          "floor": "8",
          "suite": "-",
          "use_type": "Office",
          "size_sf": "4000",
          "rent_per_sf": "$4.92",
          "page_number": 30
        },
        {
          "floor": "",
          "suite": "-",
          "use_type": "Office",
          "size_sf": "4500",
          "rent_per_sf": "$3.00",
          "page_number": 30
        }
      ]
    },
    {
      "address": "25 164 W 25th St",
      "city_state": "",
      "page_number": 31,
      "spaces": [
        {
          "floor": "",
          "suite": "-",
          "use_type": "Office",
          "size_sf": "4500",
          "rent_per_sf": "$3.00",
          "page_number": 31
        }
      ]
    },
    {
      "address": "27 151 W 26th St",
      "city_state": "",
      "page_number": 34,
      "spaces": [
        {
          "floor": "4",
          "suite": "-",
          "use_type": "Office",
          "size_sf": "4184",
          "rent_per_sf": "$3.17",
          "page_number": 34
        },
        {
          "floor": "10",
          "suite": "-",
          "use_type": "Office",
          "size_sf": "5000",
          "rent_per_sf": "$2.50",
          "page_number": 34
        }
      ]
    },
    {
      "address": "28 226 W 26th St",
      "city_state": "",
      "page_number": 35,
      "spaces": [
        {
          "floor": "4",
          "suite": "-",
          "use_type": "Office",
          "size_sf": "4184",
          "rent_per_sf": "$3.17",
          "page_number": 35
        },
        {
          "floor": "10",
          "suite": "-",
          "use_type": "Office",
          "size_sf": "5000",
          "rent_per_sf": "$2.50",
          "page_number": 35
        }
      ]
    },
    {
      "address": "30 28 W 27th St",
      "city_state": "",
      "page_number": 38,
      "spaces": [
        {
          "floor": "10",
          "suite": "-",
          "use_type": "Office",
          "size_sf": "5000",
          "rent_per_sf": "$2.50",
          "page_number": 38
        },
        {
          "floor": "2",
          "suite": "-",
          "use_type": "Office",
          "size_sf": "4000",
          "rent_per_sf": "$3.25",
          "page_number": 38
        }
      ]
    },
    {
      "address": "34 39 W 29th St",
      "city_state": "",
      "page_number": 44,
      "spaces": [
        {
          "floor": "2",
          "suite": "-",
          "use_type": "Office",
          "size_sf": "5000",
          "rent_per_sf": "$2.67",
          "page_number": 44
        },
        {
          "floor": "6",
          "suite": "-",
          "use_type": "Office",
          "size_sf": "3500",
          "rent_per_sf": "$3.00",
          "page_number": 44
        },
        {
          "floor": "7",
          "suite": "-",
          "use_type": "Office",
          "size_sf": "4500",
          "rent_per_sf": "$3.33",
          "page_number": 44
        }
      ]
    },
    {
      "address": "37 110 W 30th St",
      "city_state": "",
      "page_number": 47,
      "spaces": [
        {
          "floor": "7",
          "suite": "-",
          "use_type": "Office",
          "size_sf": "4500",
          "rent_per_sf": "$3.33",
          "page_number": 47
        },
        {
          "floor": "",
          "suite": "-",
          "use_type": "Office/Retail",
          "size_sf": "2400",
          "rent_per_sf": "$4.04",
          "page_number": 47
        },
        {
          "floor": "GRND",
          "suite": "-",
          "use_type": "Office/Retail",
          "size_sf": "2300",
          "rent_per_sf": "$4.04",
          "page_number": 47
        },
        {
          "floor": "2",
          "suite": "-",
          "use_type": "Office/Retail",
          "size_sf": "2000",
          "rent_per_sf": "",
          "page_number": 47
        },
        {
          "floor": "5",
          "suite": "-",
          "use_type": "Office/Retail",
          "size_sf": "4000",
          "rent_per_sf": "$3.50",
          "page_number": 47
        }
      ]
    },
    {
      "address": "38 234 W 30th St",
      "city_state": "",
      "page_number": 48,
      "spaces": [
        {
          "floor": "",
          "suite": "-",
          "use_type": "Office/Retail",
          "size_sf": "2400",
          "rent_per_sf": "$4.04",
          "page_number": 48
        },
        {
          "floor": "GRND",
          "suite": "-",
          "use_type": "Office/Retail",
          "size_sf": "2300",
          "rent_per_sf": "$4.04",
          "page_number": 48
        },
        {
          "floor": "2",
          "suite": "-",
          "use_type": "Office/Retail",
          "size_sf": "2000",
          "rent_per_sf": "",
          "page_number": 48
        },
        {
          "floor": "5",
          "suite": "-",
          "use_type": "Office/Retail",
          "size_sf": "4000",
          "rent_per_sf": "$3.50",
          "page_number": 48
        }
      ]
    },
    {
      "address": "43 119 Fifth Ave",
      "city_state": "",
      "page_number": 54,
      "spaces": [
        {
          "floor": "5",
          "suite": "-",
          "use_type": "Office",
          "size_sf": "4134",
          "rent_per_sf": "",
          "page_number": 54
        },
        {
          "floor": "5",
          "suite": "-",
          "use_type": "Office",
          "size_sf": "5000",
          "rent_per_sf": "$4.17",
          "page_number": 54
        },
        {
          "floor": "6",
          "suite": "-",
          "use_type": "Office",
          "size_sf": "4465",
          "rent_per_sf": "",
          "page_number": 54
        },
        {
          "floor": "17",
          "suite": "-",
          "use_type": "Office",
          "size_sf": "2121",
          "rent_per_sf": "$5.42",
          "page_number": 54
        },
        {
          "floor": "3",
          "suite": "-",
          "use_type": "Office/Retail",
          "size_sf": "4750",
          "rent_per_sf": "$2.50",
          "page_number": 54
        },
        {
          "floor": "4",
          "suite": "-",
          "use_type": "Office/Retail",
          "size_sf": "4750",
          "rent_per_sf": "$2.50",
          "page_number": 54
        },
        {
          "floor": "5",
          "suite": "-",
          "use_type": "Office/Retail",
          "size_sf": "4750",
          "rent_per_sf": "$2.50",
          "page_number": 54
        },
        {
          "floor": "6",
          "suite": "-",
          "use_type": "Office/Retail",
          "size_sf": "4750",
          "rent_per_sf": "$2.50",
          "page_number": 54
        }
      ]
    },
    {
      "address": "44 255 Fifth Ave",
      "city_state": "",
      "page_number": 55,
      "spaces": [
        {
          "floor": "5",
          "suite": "-",
          "use_type": "Office",
          "size_sf": "5000",
          "rent_per_sf": "$4.17",
          "page_number": 55
        },
        {
          "floor": "6",
          "suite": "-",
          "use_type": "Office",
          "size_sf": "4465",
          "rent_per_sf": "",
          "page_number": 55
        },
        {
          "floor": "17",
          "suite": "-",
          "use_type": "Office",
          "size_sf": "2121",
          "rent_per_sf": "$5.42",
          "page_number": 55
        },
        {
          "floor": "3",
          "suite": "-",
          "use_type": "Office/Retail",
          "size_sf": "4750",
          "rent_per_sf": "$2.50",
          "page_number": 55
        },
        {
          "floor": "4",
          "suite": "-",
          "use_type": "Office/Retail",
          "size_sf": "4750",
          "rent_per_sf": "$2.50",
          "page_number": 55
        },
        {
          "floor": "5",
          "suite": "-",
          "use_type": "Office/Retail",
          "size_sf": "4750",
          "rent_per_sf": "$2.50",
          "page_number": 55
        },
        {
          "floor": "6",
          "suite": "-",
          "use_type": "Office/Retail",
          "size_sf": "4750",
          "rent_per_sf": "$2.50",
          "page_number": 55
        }
      ]
    },
    {
      "address": "45 116 W Houston St",
      "city_state": "",
      "page_number": 56,
      "spaces": [
        {
          "floor": "6",
          "suite": "-",
          "use_type": "Office",
          "size_sf": "4465",
          "rent_per_sf": "",
          "page_number": 56
        },
        {
          "floor": "17",
          "suite": "-",
          "use_type": "Office",
          "size_sf": "2121",
          "rent_per_sf": "$5.42",
          "page_number": 56
        },
        {
          "floor": "3",
          "suite": "-",
          "use_type": "Office/Retail",
          "size_sf": "4750",
          "rent_per_sf": "$2.50",
          "page_number": 56
        },
        {
          "floor": "4",
          "suite": "-",
          "use_type": "Office/Retail",
          "size_sf": "4750",
          "rent_per_sf": "$2.50",
          "page_number": 56
        },
        {
          "floor": "5",
          "suite": "-",
          "use_type": "Office/Retail",
          "size_sf": "4750",
          "rent_per_sf": "$2.50",
          "page_number": 56
        },
        {
          "floor": "6",
          "suite": "-",
          "use_type": "Office/Retail",
          "size_sf": "4750",
          "rent_per_sf": "$2.50",
          "page_number": 56
        },
        {
          "floor": "GRND",
          "suite": "-",
          "use_type": "Office/Medical",
          "size_sf": "4000",
          "rent_per_sf": "Withheld",
          "page_number": 56
        }
      ]
    },
    {
      "address": "46 352 Park Ave",
      "city_state": "",
      "page_number": 57,
      "spaces": [
        {
          "floor": "17",
          "suite": "-",
          "use_type": "Office",
          "size_sf": "2121",
          "rent_per_sf": "$5.42",
          "page_number": 57
        },
        {
          "floor": "3",
          "suite": "-",
          "use_type": "Office/Retail",
          "size_sf": "4750",
          "rent_per_sf": "$2.50",
          "page_number": 57
        },
        {
          "floor": "4",
          "suite": "-",
          "use_type": "Office/Retail",
          "size_sf": "4750",
          "rent_per_sf": "$2.50",
          "page_number": 57
        },
        {
          "floor": "5",
          "suite": "-",
          "use_type": "Office/Retail",
          "size_sf": "4750",
          "rent_per_sf": "$2.50",
          "page_number": 57
        },
        {
          "floor": "6",
          "suite": "-",
          "use_type": "Office/Retail",
          "size_sf": "4750",
          "rent_per_sf": "$2.50",
          "page_number": 57
        },
        {
          "floor": "GRND",
          "suite": "-",
          "use_type": "Office/Medical",
          "size_sf": "4000",
          "rent_per_sf": "Withheld",
          "page_number": 57
        },
        {
          "floor": "4",
          "suite": "-",
          "use_type": "Office",
          "size_sf": "4890",
          "rent_per_sf": "",
          "page_number": 57
        },
        {
          "floor": "5",
          "suite": "-",
          "use_type": "Office",
          "size_sf": "4890",
          "rent_per_sf": "",
          "page_number": 57
        },
        {
          "floor": "6",
          "suite": "-",
          "use_type": "Office",
          "size_sf": "4890",
          "rent_per_sf": "",
          "page_number": 57
        }
      ]
    },
    {
      "address": "47 838 Sixth Ave",
      "city_state": "",
      "page_number": 58,
      "spaces": [
        {
          "floor": "3",
          "suite": "-",
          "use_type": "Office/Retail",
          "size_sf": "4750",
          "rent_per_sf": "$2.50",
          "page_number": 58
        },
        {
          "floor": "4",
          "suite": "-",
          "use_type": "Office/Retail",
          "size_sf": "4750",
          "rent_per_sf": "$2.50",
          "page_number": 58
        },
        {
          "floor": "5",
          "suite": "-",
          "use_type": "Office/Retail",
          "size_sf": "4750",
          "rent_per_sf": "$2.50",
          "page_number": 58
        },
        {
          "floor": "6",
          "suite": "-",
          "use_type": "Office/Retail",
          "size_sf": "4750",
          "rent_per_sf": "$2.50",
          "page_number": 58
        },
        {
          "floor": "GRND",
          "suite": "-",
          "use_type": "Office/Medical",
          "size_sf": "4000",
          "rent_per_sf": "Withheld",
          "page_number": 58
        },
        {
          "floor": "4",
          "suite": "-",
          "use_type": "Office",
          "size_sf": "4890",
          "rent_per_sf": "",
          "page_number": 58
        },
        {
          "floor": "5",
          "suite": "-",
          "use_type": "Office",
          "size_sf": "4890",
          "rent_per_sf": "",
          "page_number": 58
        },
        {
          "floor": "6",
          "suite": "-",
          "use_type": "Office",
          "size_sf": "4890",
          "rent_per_sf": "",
          "page_number": 58
        }
      ]
    },
    {
      "address": "48 233 3rd Ave",
      "city_state": "",
      "page_number": 59,
      "spaces": [
        {
          "floor": "GRND",
          "suite": "-",
          "use_type": "Office/Medical",
          "size_sf": "4000",
          "rent_per_sf": "Withheld",
          "page_number": 59
        },
        {
          "floor": "4",
          "suite": "-",
          "use_type": "Office",
          "size_sf": "4890",
          "rent_per_sf": "",
          "page_number": 59
        },
        {
          "floor": "5",
          "suite": "-",
          "use_type": "Office",
          "size_sf": "4890",
          "rent_per_sf": "",
          "page_number": 59
        },
        {
          "floor": "6",
          "suite": "-",
          "use_type": "Office",
          "size_sf": "4890",
          "rent_per_sf": "",
          "page_number": 59
        }
      ]
    },
    {
      "address": "50 25 W 14th St",
      "city_state": "",
      "page_number": 63,
      "spaces": [
        {
          "floor": "11",
          "suite": "-",
          "use_type": "Office",
          "size_sf": "3921",
          "rent_per_sf": "",
          "page_number": 63
        },
        {
          "floor": "4",
          "suite": "-",
          "use_type": "Office",
          "size_sf": "4100",
          "rent_per_sf": "",
          "page_number": 63
        }
      ]
    },
    {
      "address": "51 22 W 19th St",
      "city_state": "",
      "page_number": 64,
      "spaces": [
        {
          "floor": "11",
          "suite": "-",
          "use_type": "Office",
          "size_sf": "3921",
          "rent_per_sf": "",
          "page_number": 64
        },
        {
          "floor": "4",
          "suite": "-",
          "use_type": "Office",
          "size_sf": "4100",
          "rent_per_sf": "",
          "page_number": 64
        },
        {
          "floor": "12",
          "suite": "-",
          "use_type": "Office",
          "size_sf": "5000",
          "rent_per_sf": "",
          "page_number": 64
        },
        {
          "floor": "15",
          "suite": "-",
          "use_type": "Office",
          "size_sf": "5000",
          "rent_per_sf": "",
          "page_number": 64
        }
      ]
    },
    {
      "address": "52 220 W 19th St",
      "city_state": "",
      "page_number": 65,
      "spaces": [
        {
          "floor": "11",
          "suite": "-",
          "use_type": "Office",
          "size_sf": "3921",
          "rent_per_sf": "",
          "page_number": 65
        },
        {
          "floor": "4",
          "suite": "-",
          "use_type": "Office",
          "size_sf": "4100",
          "rent_per_sf": "",
          "page_number": 65
        },
        {
          "floor": "12",
          "suite": "-",
          "use_type": "Office",
          "size_sf": "5000",
          "rent_per_sf": "",
          "page_number": 65
        },
        {
          "floor": "15",
          "suite": "-",
          "use_type": "Office",
          "size_sf": "5000",
          "rent_per_sf": "",
          "page_number": 65
        }
      ]
    },
    {
      "address": "54 36 W 25th St",
      "city_state": "",
      "page_number": 67,
      "spaces": [
        {
          "floor": "12",
          "suite": "-",
          "use_type": "Office",
          "size_sf": "5000",
          "rent_per_sf": "",
          "page_number": 67
        },
        {
          "floor": "15",
          "suite": "-",
          "use_type": "Office",
          "size_sf": "5000",
          "rent_per_sf": "",
          "page_number": 67
        },
        {
          "floor": "3",
          "suite": "-",
          "use_type": "Office",
          "size_sf": "5000",
          "rent_per_sf": "",
          "page_number": 67
        },
        {
          "floor": "4",
          "suite": "-",
          "use_type": "Office",
          "size_sf": "5000",
          "rent_per_sf": "",
          "page_number": 67
        }
      ]
    },
    {
      "address": "55 125 W 25th St",
      "city_state": "",
      "page_number": 68,
      "spaces": [
        {
          "floor": "3",
          "suite": "-",
          "use_type": "Office",
          "size_sf": "5000",
          "rent_per_sf": "",
          "page_number": 68
        },
        {
          "floor": "4",
          "suite": "-",
          "use_type": "Office",
          "size_sf": "5000",
          "rent_per_sf": "",
          "page_number": 68
        },
        {
          "floor": "4",
          "suite": "-",
          "use_type": "Office",
          "size_sf": "5000",
          "rent_per_sf": "",
          "page_number": 68
        },
        {
          "floor": "8",
          "suite": "-",
          "use_type": "Office",
          "size_sf": "5000",
          "rent_per_sf": "",
          "page_number": 68
        },
        {
          "floor": "12",
          "suite": "-",
          "use_type": "Office",
          "size_sf": "5000",
          "rent_per_sf": "",
          "page_number": 68
        }
      ]
    },
    {
      "address": "56 25 W 26th St",
      "city_state": "",
      "page_number": 69,
      "spaces": [
        {
          "floor": "3",
          "suite": "-",
          "use_type": "Office",
          "size_sf": "5000",
          "rent_per_sf": "",
          "page_number": 69
        },
        {
          "floor": "4",
          "suite": "-",
          "use_type": "Office",
          "size_sf": "5000",
          "rent_per_sf": "",
          "page_number": 69
        },
        {
          "floor": "4",
          "suite": "-",
          "use_type": "Office",
          "size_sf": "5000",
          "rent_per_sf": "",
          "page_number": 69
        },
        {
          "floor": "8",
          "suite": "-",
          "use_type": "Office",
          "size_sf": "5000",
          "rent_per_sf": "",
          "page_number": 69
        },
        {
          "floor": "12",
          "suite": "-",
          "use_type": "Office",
          "size_sf": "5000",
          "rent_per_sf": "",
          "page_number": 69
        },
        {
          "floor": "",
          "suite": "-",
          "use_type": "Office",
          "size_sf": "4400",
          "rent_per_sf": "Withheld",
          "page_number": 69
        }
      ]
    },
    {
      "address": "57 109 W 27th St",
      "city_state": "",
      "page_number": 71,
      "spaces": [
        {
          "floor": "4",
          "suite": "-",
          "use_type": "Office",
          "size_sf": "5000",
          "rent_per_sf": "",
          "page_number": 71
        },
        {
          "floor": "8",
          "suite": "-",
          "use_type": "Office",
          "size_sf": "5000",
          "rent_per_sf": "",
          "page_number": 71
        },
        {
          "floor": "12",
          "suite": "-",
          "use_type": "Office",
          "size_sf": "5000",
          "rent_per_sf": "",
          "page_number": 71
        },
        {
          "floor": "",
          "suite": "-",
          "use_type": "Office",
          "size_sf": "4400",
          "rent_per_sf": "Withheld",
          "page_number": 71
        },
        {
          "floor": "9",
          "suite": "-",
          "use_type": "Office",
          "size_sf": "5000",
          "rent_per_sf": "",
          "page_number": 71
        }
      ]
    },
    {
      "address": "59 37 E 28th St",
      "city_state": "",
      "page_number": 73,
      "spaces": [
        {
          "floor": "",
          "suite": "-",
          "use_type": "Office",
          "size_sf": "4400",
          "rent_per_sf": "Withheld",
          "page_number": 73
        },
        {
          "floor": "9",
          "suite": "-",
          "use_type": "Office",
          "size_sf": "5000",
          "rent_per_sf": "",
          "page_number": 73
        }
      ]
    },
    {
      "address": "60 37 W 28th St",
      "city_state": "",
      "page_number": 74,
      "spaces": [
        {
          "floor": "9",
          "suite": "-",
          "use_type": "Office",
          "size_sf": "5000",
          "rent_per_sf": "",
          "page_number": 74
        },
        {
          "floor": "7",
          "suite": "-",
          "use_type": "Office",
          "size_sf": "4832",
          "rent_per_sf": "",
          "page_number": 74
        }
      ]
    },
    {
      "address": "61 205 W 28th St",
      "city_state": "",
      "page_number": 75,
      "spaces": [
        {
          "floor": "7",
          "suite": "-",
          "use_type": "Office",
          "size_sf": "4832",
          "rent_per_sf": "",
          "page_number": 75
        },
        {
          "floor": "",
          "suite": "-",
          "use_type": "Office/Retail",
          "size_sf": "4330",
          "rent_per_sf": "Withheld",
          "page_number": 75
        }
      ]
    },
    {
      "address": "62 104 W 29th St",
      "city_state": "",
      "page_number": 76,
      "spaces": [
        {
          "floor": "7",
          "suite": "-",
          "use_type": "Office",
          "size_sf": "4832",
          "rent_per_sf": "",
          "page_number": 76
        },
        {
          "floor": "",
          "suite": "-",
          "use_type": "Office/Retail",
          "size_sf": "4330",
          "rent_per_sf": "Withheld",
          "page_number": 76
        }
      ]
    },
    {
      "address": "64 22 E 30th St",
      "city_state": "",
      "page_number": 78,
      "spaces": [
        {
          "floor": "",
          "suite": "-",
          "use_type": "Office/Retail",
          "size_sf": "4330",
          "rent_per_sf": "Withheld",
          "page_number": 78
        },
        {
          "floor": "1",
          "suite": "-",
          "use_type": "Office/Retail",
          "size_sf": "2897",
          "rent_per_sf": "",
          "page_number": 78
        },
        {
          "floor": "2",
          "suite": "-",
          "use_type": "Office",
          "size_sf": "2900",
          "rent_per_sf": "",
          "page_number": 78
        },
        {
          "floor": "3",
          "suite": "-",
          "use_type": "Office",
          "size_sf": "2966",
          "rent_per_sf": "",
          "page_number": 78
        },
        {
          "floor": "5",
          "suite": "-",
          "use_type": "Office",
          "size_sf": "2984",
          "rent_per_sf": "",
          "page_number": 78
        },
        {
          "floor": "6",
          "suite": "-",
          "use_type": "Office",
          "size_sf": "2988",
          "rent_per_sf": "",
          "page_number": 78
        },
        {
          "floor": "11",
          "suite": "-",
          "use_type": "Office",
          "size_sf": "4578",
          "rent_per_sf": "",
          "page_number": 78
        }
      ]
    },
    {
      "address": "66 31 Bond St",
      "city_state": "",
      "page_number": 80,
      "spaces": [
        {
          "floor": "1",
          "suite": "-",
          "use_type": "Office/Retail",
          "size_sf": "2897",
          "rent_per_sf": "",
          "page_number": 80
        },
        {
          "floor": "2",
          "suite": "-",
          "use_type": "Office",
          "size_sf": "2900",
          "rent_per_sf": "",
          "page_number": 80
        },
        {
          "floor": "3",
          "suite": "-",
          "use_type": "Office",
          "size_sf": "2966",
          "rent_per_sf": "",
          "page_number": 80
        },
        {
          "floor": "5",
          "suite": "-",
          "use_type": "Office",
          "size_sf": "2984",
          "rent_per_sf": "",
          "page_number": 80
        },
        {
          "floor": "6",
          "suite": "-",
          "use_type": "Office",
          "size_sf": "2988",
          "rent_per_sf": "",
          "page_number": 80
        },
        {
          "floor": "11",
          "suite": "-",
          "use_type": "Office",
          "size_sf": "4578",
          "rent_per_sf": "",
          "page_number": 80
        },
        {
          "floor": "GRND",
          "suite": "774",
          "use_type": "Office/Retail",
          "size_sf": "725",
          "rent_per_sf": "Withheld",
          "page_number": 80
        }
      ]
    },
    {
      "address": "73 166 Crosby St",
      "city_state": "",
      "page_number": 89,
      "spaces": [
        {
          "floor": "5",
          "suite": "-",
          "use_type": "Office",
          "size_sf": "1000",
          "rent_per_sf": "",
          "page_number": 89
        },
        {
          "floor": "3",
          "suite": "-",
          "use_type": "Office",
          "size_sf": "100",
          "rent_per_sf": "",
          "page_number": 89
        }
      ]
    },
    {
      "address": "74 245 Fifth Ave",
      "city_state": "",
      "page_number": 90,
      "spaces": [
        {
          "floor": "3",
          "suite": "-",
          "use_type": "Office",
          "size_sf": "100",
          "rent_per_sf": "",
          "page_number": 90
        }
      ]
    },
    {
      "address": "75 246 Fifth Ave",
      "city_state": "",
      "page_number": 91,
      "spaces": [
        {
          "floor": "3",
          "suite": "-",
          "use_type": "Office",
          "size_sf": "100",
          "rent_per_sf": "",
          "page_number": 91
        }
      ]
    },
    {
      "address": "76 261 Fifth Ave",
      "city_state": "",
      "page_number": 92,
      "spaces": [
        {
          "floor": "",
          "suite": "8",
          "use_type": "815/817/819Office",
          "size_sf": "4388",
          "rent_per_sf": "Withheld",
          "page_number": 92
        }
      ]
    },
    {
      "address": "77 333 Park Ave",
      "city_state": "",
      "page_number": 93,
      "spaces": [
        {
          "floor": "",
          "suite": "8",
          "use_type": "815/817/819Office",
          "size_sf": "4388",
          "rent_per_sf": "Withheld",
          "page_number": 93
        },
        {
          "floor": "6",
          "suite": "-",
          "use_type": "Office",
          "size_sf": "4765",
          "rent_per_sf": "",
          "page_number": 93
        },
        {
          "floor": "7",
          "suite": "-",
          "use_type": "Office",
          "size_sf": "4748",
          "rent_per_sf": "",
          "page_number": 93
        },
        {
          "floor": "8",
          "suite": "-",
          "use_type": "Office",
          "size_sf": "4765",
          "rent_per_sf": "",
          "page_number": 93
        },
        {
          "floor": "9",
          "suite": "-",
          "use_type": "Office",
          "size_sf": "2062",
          "rent_per_sf": "",
          "page_number": 93
        }
      ]
    },
    {
      "address": "78 377 Park Ave",
      "city_state": "",
      "page_number": 94,
      "spaces": [
        {
          "floor": "",
          "suite": "8",
          "use_type": "815/817/819Office",
          "size_sf": "4388",
          "rent_per_sf": "Withheld",
          "page_number": 94
        },
        {
          "floor": "6",
          "suite": "-",
          "use_type": "Office",
          "size_sf": "4765",
          "rent_per_sf": "",
          "page_number": 94
        },
        {
          "floor": "7",
          "suite": "-",
          "use_type": "Office",
          "size_sf": "4748",
          "rent_per_sf": "",
          "page_number": 94
        },
        {
          "floor": "8",
          "suite": "-",
          "use_type": "Office",
          "size_sf": "4765",
          "rent_per_sf": "",
          "page_number": 94
        },
        {
          "floor": "9",
          "suite": "-",
          "use_type": "Office",
          "size_sf": "2062",
          "rent_per_sf": "",
          "page_number": 94
        }
      ]
    },
    {
      "address": "79 381 Park Ave",
      "city_state": "",
      "page_number": 96,
      "spaces": [
        {
          "floor": "",
          "suite": "8",
          "use_type": "815/817/819Office",
          "size_sf": "4388",
          "rent_per_sf": "Withheld",
          "page_number": 96
        },
        {
          "floor": "6",
          "suite": "-",
          "use_type": "Office",
          "size_sf": "4765",
          "rent_per_sf": "",
          "page_number": 96
        },
        {
          "floor": "7",
          "suite": "-",
          "use_type": "Office",
          "size_sf": "4748",
          "rent_per_sf": "",
          "page_number": 96
        },
        {
          "floor": "8",
          "suite": "-",
          "use_type": "Office",
          "size_sf": "4765",
          "rent_per_sf": "",
          "page_number": 96
        },
        {
          "floor": "9",
          "suite": "-",
          "use_type": "Office",
          "size_sf": "2062",
          "rent_per_sf": "",
          "page_number": 96
        },
        {
          "floor": "6",
          "suite": "-",
          "use_type": "Office",
          "size_sf": "4444",
          "rent_per_sf": "",
          "page_number": 96
        }
      ]
    },
    {
      "address": "80 1 Saint Marks Pl",
      "city_state": "",
      "page_number": 97,
      "spaces": [
        {
          "floor": "6",
          "suite": "-",
          "use_type": "Office",
          "size_sf": "4765",
          "rent_per_sf": "",
          "page_number": 97
        },
        {
          "floor": "7",
          "suite": "-",
          "use_type": "Office",
          "size_sf": "4748",
          "rent_per_sf": "",
          "page_number": 97
        },
        {
          "floor": "8",
          "suite": "-",
          "use_type": "Office",
          "size_sf": "4765",
          "rent_per_sf": "",
          "page_number": 97
        },
        {
          "floor": "9",
          "suite": "-",
          "use_type": "Office",
          "size_sf": "2062",
          "rent_per_sf": "",
          "page_number": 97
        },
        {
          "floor": "6",
          "suite": "-",
          "use_type": "Office",
          "size_sf": "4444",
          "rent_per_sf": "",
          "page_number": 97
        },
        {
          "floor": "3",
          "suite": "-",
          "use_type": "Office",
          "size_sf": "3900",
          "rent_per_sf": "",
          "page_number": 97
        },
        {
          "floor": "5",
          "suite": "-",
          "use_type": "Office",
          "size_sf": "3900",
          "rent_per_sf": "",
          "page_number": 97
        }
      ]
    },
    {
      "address": "81 330 Seventh Ave",
      "city_state": "",
      "page_number": 98,
      "spaces": [
        {
          "floor": "6",
          "suite": "-",
          "use_type": "Office",
          "size_sf": "4444",
          "rent_per_sf": "",
          "page_number": 98
        },
        {
          "floor": "3",
          "suite": "-",
          "use_type": "Office",
          "size_sf": "3900",
          "rent_per_sf": "",
          "page_number": 98
        },
        {
          "floor": "5",
          "suite": "-",
          "use_type": "Office",
          "size_sf": "3900",
          "rent_per_sf": "",
          "page_number": 98
        },
        {
          "floor": "4",
          "suite": "-",
          "use_type": "Office",
          "size_sf": "4796",
          "rent_per_sf": "",
          "page_number": 98
        },
        {
          "floor": "5",
          "suite": "-",
          "use_type": "Office",
          "size_sf": "4796",
          "rent_per_sf": "",
          "page_number": 98
        },
        {
          "floor": "6",
          "suite": "-",
          "use_type": "Office",
          "size_sf": "4796",
          "rent_per_sf": "",
          "page_number": 98
        }
      ]
    },
    {
      "address": "82 350 Seventh Ave",
      "city_state": "",
      "page_number": 99,
      "spaces": [
        {
          "floor": "6",
          "suite": "-",
          "use_type": "Office",
          "size_sf": "4444",
          "rent_per_sf": "",
          "page_number": 99
        },
        {
          "floor": "3",
          "suite": "-",
          "use_type": "Office",
          "size_sf": "3900",
          "rent_per_sf": "",
          "page_number": 99
        },
        {
          "floor": "5",
          "suite": "-",
          "use_type": "Office",
          "size_sf": "3900",
          "rent_per_sf": "",
          "page_number": 99
        },
        {
          "floor": "4",
          "suite": "-",
          "use_type": "Office",
          "size_sf": "4796",
          "rent_per_sf": "",
          "page_number": 99
        },
        {
          "floor": "5",
          "suite": "-",
          "use_type": "Office",
          "size_sf": "4796",
          "rent_per_sf": "",
          "page_number": 99
        },
        {
          "floor": "6",
          "suite": "-",
          "use_type": "Office",
          "size_sf": "4796",
          "rent_per_sf": "",
          "page_number": 99
        }
      ]
    },
    {
      "address": "85 99 University Pl",
      "city_state": "",
      "page_number": 102,
      "spaces": [
        {
          "floor": "4",
          "suite": "-",
          "use_type": "Office",
          "size_sf": "4796",
          "rent_per_sf": "",
          "page_number": 102
        },
        {
          "floor": "5",
          "suite": "-",
          "use_type": "Office",
          "size_sf": "4796",
          "rent_per_sf": "",
          "page_number": 102
        },
        {
          "floor": "6",
          "suite": "-",
          "use_type": "Office",
          "size_sf": "4796",
          "rent_per_sf": "",
          "page_number": 102
        }
      ]
    }
  ],
  "summary": {
    "total_retail_records": 62,
    "total_office_records": 56,
    "total_retail_spaces": 195,
    "total_office_spaces": 221
  }
}